sansio_tools/__init__.py
sansio_tools/_util.py
sansio_tools/parser.py
sansio_tools/py.typed
sansio_tools/queue.py
sansio_tools-1.0.0.dist-info/licenses/AUTHORS.md
sansio_tools-1.0.0.dist-info/licenses/LICENSE
sansio_tools-1.0.0.dist-info/METADATA
sansio_tools-1.0.0.dist-info/WHEEL
sansio_tools-1.0.0.dist-info/top_level.txt
sansio_tools-1.0.0.dist-info/RECORD
