Metadata-Version: 2.4
Name: sansio_tools
Version: 1.0.0
Summary: Tools for building Sans IO libraries
Author-email: Eduard Christian Dumitrescu <eduard.c.dumitrescu@gmail.com>
Maintainer-email: Eduard Christian Dumitrescu <eduard.c.dumitrescu@gmail.com>
License: MIT
Project-URL: Homepage, https://hydra.ecd.space/deaduard/sansio-tools/
Project-URL: Changelog, https://hydra.ecd.space/deaduard/sansio-tools/file?name=CHANGELOG.md&ci=trunk
Classifier: Programming Language :: Python :: 3
License-File: LICENSE
License-File: AUTHORS.md
Dynamic: license-file
